gramlib/__init__.py
gramlib/gram.py
libgram-2.0.1.dist-info/METADATA
libgram-2.0.1.dist-info/WHEEL
libgram-2.0.1.dist-info/top_level.txt
libgram-2.0.1.dist-info/RECORD
